StateManager.py
pgsm-0.0.1.dist-info/METADATA
pgsm-0.0.1.dist-info/WHEEL
pgsm-0.0.1.dist-info/top_level.txt
pgsm-0.0.1.dist-info/RECORD
