Metadata-Version: 2.1
Name: pgsm
Version: 0.0.1
Summary: A simple state manager for pygame.
Author-email: Rashid Harvey <r.harvey@outlook.de>
Project-URL: Homepage, https://github.com/theRealProHacker/StateManager
Project-URL: Bug Tracker, https://github.com/theRealProHacker/StateManager/issues
Classifier: Programming Language :: Python :: 3
Classifier: Operating System :: OS Independent
Classifier: License :: OSI Approved :: MIT License
Requires-Python: >=3.10
